dbt_loom/__init__.py
dbt_loom/config.py
dbt_loom/logging.py
dbt_loom/manifests.py
dbt_loom/shims.py
dbt_loom/clients/az_blob.py
dbt_loom/clients/dbt_cloud.py
dbt_loom/clients/dbx.py
dbt_loom/clients/gcs.py
dbt_loom/clients/paradime.py
dbt_loom/clients/s3.py
dbt_loom/clients/snowflake_stage.py
dbt_loom-0.9.4.dist-info/METADATA
dbt_loom-0.9.4.dist-info/WHEEL
dbt_loom-0.9.4.dist-info/licenses/LICENSE
dbt_loom-0.9.4.dist-info/RECORD
