Metadata-Version: 2.4
Name: dbt-loom
Version: 0.9.4
Summary: A dbt-core plugin to import public nodes in multi-project deployments.
Author-email: Nicholas Yager <yager@nicholasyager.com>
License-File: LICENSE
Requires-Python: <4.0,>=3.9
Requires-Dist: azure-identity<2,>=1.15.0
Requires-Dist: azure-storage-blob<13,>=12.19.0
Requires-Dist: boto3<2,>=1.28.84
Requires-Dist: dbt-core<1.12.0,>=1.6.0
Requires-Dist: google-auth>=2.40.3
Requires-Dist: google-cloud-storage<4,>=2.13.0
Requires-Dist: paradime-io<5,>=4.11.0
Requires-Dist: requests<3,>=2.31.0
Requires-Dist: types-networkx<4,>=3.2.1.20240313
Requires-Dist: types-pyyaml<7,>=6.0.12.12
Provides-Extra: snowflake
